aktools/__init__.py
aktools/__main__.py
aktools/cli.py
aktools/config.py
aktools/datasets.py
aktools/main.py
aktools/utils.py
aktools/api_debug/__init__.py
aktools/api_debug/local_debug.py
aktools/assets/__init__.py
aktools/assets/html/__init__.py
aktools/assets/html/akscript.html
aktools/assets/html/homepage.html
aktools/assets/images/__init__.py
aktools/assets/images/favicon.ico
aktools/core/__init__.py
aktools/core/api.py
aktools/database/__init__.py
aktools/database/connection.py
aktools/login/__init__.py
aktools/login/user_login.py
aktools/model/__init__.py
aktools/schema/__init__.py
aktools/schema/version.py
aktools-0.0.90.dist-info/licenses/LICENSE
tests/__init__.py
tests/test_cli.py
tests/test_demo.py
aktools-0.0.90.dist-info/METADATA
aktools-0.0.90.dist-info/WHEEL
aktools-0.0.90.dist-info/top_level.txt
aktools-0.0.90.dist-info/RECORD
